standard_precip/base_sp.py
standard_precip/spi.py
standard_precip/utils.py
standard_precip/lmoments/distr.py
standard_precip/lmoments/lmoments_base.py
standard_precip/lmoments/stats.py
standard_precip-1.0.dist-info/LICENSE
standard_precip-1.0.dist-info/METADATA
standard_precip-1.0.dist-info/WHEEL
standard_precip-1.0.dist-info/top_level.txt
standard_precip-1.0.dist-info/RECORD
