Metadata-Version: 2.1
Name: standard-precip
Version: 1.0
Summary: Functions to calculate SPI and SPEI
Home-page: http://github.com/e-baumer/standard_precip
Author: Eric Nussbaumer
Author-email: ebaumer@gmail.com
License: Apache License 2.0
Platform: UNKNOWN
Requires-Python: >=3.6
Requires-Dist: numpy (>=1.19.0)
Requires-Dist: matplotlib (>=3.1.2)
Requires-Dist: scipy (>=1.5.4)
Requires-Dist: pandas (>=1.1.5)
